ca_certificates/__init__.py
pokemon_app_sdk-1.9.12.dist-info/METADATA
pokemon_app_sdk-1.9.12.dist-info/WHEEL
pokemon_app_sdk-1.9.12.dist-info/top_level.txt
pokemon_app_sdk-1.9.12.dist-info/RECORD
